LICENSE.md
README.md
pyproject.toml
tacklebox/__init__.py
tacklebox/entrypoint.py
tacklebox/sync.py
tacklebox/utils.py
tacklebox/version.py
tacklebox/commands/__init__.py
tacklebox/commands/clipboard.py
tacklebox/commands/spectacle.py
tacklebox/commands/version.py
tacklebox_cli-0.2.6.dist-info/METADATA
tacklebox_cli-0.2.6.dist-info/WHEEL
tacklebox_cli-0.2.6.dist-info/entry_points.txt
tacklebox_cli-0.2.6.dist-info/licenses/LICENSE.md
tacklebox_cli-0.2.6.dist-info/RECORD
