Metadata-Version: 2.4
Name: tacklebox-cli
Version: 0.2.6
Summary: A small collection of CLI utilities.
Project-URL: Homepage, https://c.csw.im/cswimr/tacklebox
Project-URL: Issues, https://c.csw.im/cswimr/tacklebox/issues
Project-URL: source_archive, https://c.csw.im/cswimr/tacklebox/archive/7d8c5beaa8fce3cf47c233f13720ed44548464bd.tar.gz
Author-email: cswimr <seaswimmerthefsh@gmail.com>
License-Expression: MIT
License-File: LICENSE.md
Classifier: License :: OSI Approved :: MIT License
Classifier: Programming Language :: Python
Classifier: Programming Language :: Python :: 3.11
Classifier: Programming Language :: Python :: 3.12
Classifier: Programming Language :: Python :: 3.13
Requires-Python: >=3.11
Requires-Dist: desktop-notifier>=6.1.0
Requires-Dist: platformdirs>=4.3.0
Requires-Dist: zipline-py[cli]>=0.27.0
